Functions/DataBase.py
Functions/Functions.py
Functions/__init__.py
Functionss-0.0.1.dist-info/METADATA
Functionss-0.0.1.dist-info/WHEEL
Functionss-0.0.1.dist-info/top_level.txt
Functionss-0.0.1.dist-info/RECORD
